LICENSE
MANIFEST.in
README.rst
setup.cfg
setup.py
Pyramid_Igniter.egg-info/PKG-INFO
Pyramid_Igniter.egg-info/SOURCES.txt
Pyramid_Igniter.egg-info/dependency_links.txt
Pyramid_Igniter.egg-info/not-zip-safe
Pyramid_Igniter.egg-info/requires.txt
Pyramid_Igniter.egg-info/top_level.txt
pyramid_igniter/__init__.py
pyramid_igniter.egg-info/SOURCES.txt
pyramid_igniter/templates/master.bootstrap2.jinja2
pyramid_igniter/templates/master.bootstrap2.mako
pyramid_igniter/templates/master.bootstrap3.jinja2
pyramid_igniter/templates/master.bootstrap3.mako