Metadata-Version: 1.1
Name: pyramid-igniter
Version: 0.2.4
Summary: Flexible class-based views and Twitter Bootstrap for Pyramid
Home-page: https://github.com/tark-hidden/pyramid_igniter
Author: Tark
Author-email: tark.hidden@gmail.com
License: BSD
Keywords: bootstrap pyramid igniter
Platform: any
Classifier: Environment :: Web Environment
Classifier: Intended Audience :: Developers
Classifier: License :: OSI Approved :: BSD License
Classifier: Operating System :: OS Independent
Classifier: Programming Language :: Python
Classifier: Programming Language :: Python :: 2
Classifier: Programming Language :: Python :: 2.6
Classifier: Programming Language :: Python :: 2.7
Classifier: Programming Language :: Python :: 3
Classifier: Programming Language :: Python :: 3.3
Classifier: Programming Language :: Python :: 3.4
Classifier: Topic :: Internet :: WWW/HTTP :: Dynamic Content
Classifier: Topic :: Software Development :: Libraries :: Python Modules
